watchgate/__init__.py
watchgate/__main__.py
watchgate/main.py
watchgate/server_manager.py
watchgate/cli/__init__.py
watchgate/cli/startup_error_handler.py
watchgate/cli/startup_error_notifier.py
watchgate/config/__init__.py
watchgate/config/loader.py
watchgate/config/models.py
watchgate/plugins/__init__.py
watchgate/plugins/interfaces.py
watchgate/plugins/manager.py
watchgate/plugins/auditing/__init__.py
watchgate/plugins/auditing/base.py
watchgate/plugins/auditing/common_event_format.py
watchgate/plugins/auditing/csv.py
watchgate/plugins/auditing/human_readable.py
watchgate/plugins/auditing/json_lines.py
watchgate/plugins/auditing/opentelemetry.py
watchgate/plugins/auditing/syslog.py
watchgate/plugins/security/__init__.py
watchgate/plugins/security/filesystem_server.py
watchgate/plugins/security/pii.py
watchgate/plugins/security/prompt_injection.py
watchgate/plugins/security/secrets.py
watchgate/plugins/security/tool_allowlist.py
watchgate/protocol/__init__.py
watchgate/protocol/errors.py
watchgate/protocol/messages.py
watchgate/protocol/validation.py
watchgate/proxy/__init__.py
watchgate/proxy/server.py
watchgate/proxy/stdio_server.py
watchgate/transport/__init__.py
watchgate/transport/base.py
watchgate/transport/errors.py
watchgate/transport/stdio.py
watchgate/tui/__init__.py
watchgate/tui/app.py
watchgate/tui/path_suggester.py
watchgate/tui/screens/__init__.py
watchgate/tui/screens/config_editor.py
watchgate/tui/screens/config_picker_modal.py
watchgate/tui/screens/config_selector.py
watchgate/tui/screens/directory_browser_modal.py
watchgate/tui/screens/directory_dialog.py
watchgate/utils/__init__.py
watchgate/utils/encoding.py
watchgate/utils/namespacing.py
watchgate/utils/paths.py
watchgate/utils/version.py
watchgate-0.1.0.dist-info/METADATA
watchgate-0.1.0.dist-info/WHEEL
watchgate-0.1.0.dist-info/entry_points.txt
watchgate-0.1.0.dist-info/licenses/LICENSE
watchgate-0.1.0.dist-info/RECORD
