Metadata-Version: 2.4
Name: watchgate
Version: 0.1.0
Summary: Secure MCP gateway with auditing and access control
License: Apache-2.0
License-File: LICENSE
Requires-Python: >=3.11
Requires-Dist: aiohttp==3.12.4
Requires-Dist: pathspec==0.12.1
Requires-Dist: pydantic==2.11.5
Requires-Dist: pyyaml==6.0.2
Requires-Dist: textual>=0.47.0
Provides-Extra: dev
Requires-Dist: black>=23.0; extra == 'dev'
Requires-Dist: mypy>=1.5; extra == 'dev'
Requires-Dist: pytest-asyncio>=0.21; extra == 'dev'
Requires-Dist: pytest-cov>=4.0; extra == 'dev'
Requires-Dist: pytest>=7.0; extra == 'dev'
Requires-Dist: ruff>=0.0.290; extra == 'dev'
